<?xml version="1.0" encoding="UTF-8"?>
<TaskList Name = "Training" >
	<Sequence ID = "Training_OnListStart" >
		
	</Sequence>
	
	<Sequence ID = "Training_OnListEnd" >
		<Task ID="0" TaskType="TaskUserInterface" Command="Hide" UI="TRAINING_TIPS"/>
	</Sequence>

<!-- Training_100 START-->

	<Sequence ID = "Training_100_OnBegin" >
		<Task ID="00" TaskType="TaskEnvironmentInteraction" Code="Door" IsLocked="true" GameObject_ID="TrainingExitDoor" />
		<Task ID="0" TaskType="TaskAudio" AudClip="TrainingGreetings" IsStart="true" IsLoop="false" Volume="1.0" SrcType="AUD_SRC_SFX" IsPooled="false" GameObjID="TrainingSpeaker"/>
	
	    <!-- Helmet -->
	    <!--Task ID="1" TaskType="TaskItem" Code="Activate" Item_ID="HELMET_Locker_Item" ItemType="ITEM_HELMET" ObjectiveTrigger="ObjectivePickupHelmet_Level_102" StrengthPercentage="100" Position="-5.824,0.779,-7.222" Rotation="-9,90,0.0"/-->
		
		<!-- Weapons -->
	    <Task ID="1" TaskType="TaskItem" Code="Activate" Item_ID="FN57_Bunker_Item" ItemType="ITEM_FN57" BulletCount="0" ObjectiveTrigger="ObjectivePickupHandgun_Level_105" Position="-2.6265,-2.4402,22.9345" Rotation="-0.105,127.388,-90.926"/>
		<Task ID="2" TaskType="TaskItem" Code="Activate" Item_ID="AK47_Bunker_Item" ItemType="ITEM_AK47" IsInteractive ="false" BulletCount="0" ObjectiveTrigger="ObjectivePickupAssault" Position="-4.4431,-2.119998,26.445" Rotation="-77.244,-82.80801,-12.326"/>
		<Task ID="3" TaskType="TaskItem" Code="Activate" Item_ID="Thompson_Bunker_Item" ItemType="ITEM_THOMPSON" IsInteractive ="false" BulletCount="0" ObjectiveTrigger="ObjectivePickupAssault" Position="0.953,-3.16,26.335" Rotation="-4.25,27.066,-91.815"/>
		
		
		<!-- Secondary Ammo -->
		<Task ID="1" TaskType="TaskItem" Code="Activate" Item_ID="FN57Bullets_1" ItemType="ITEM_SECONDARY_BULLETS" IsInteractive ="false" ObjectiveTrigger="ObjectivePickupHandgunBullets_Level_106" BulletCount="30" Position="1.683,-2.811,23.544" 		Rotation="0.0,-155.433,0.0"/>
		<Task ID="2" TaskType="TaskItem" Code="Activate" Item_ID="FN57Bullets_2" ItemType="ITEM_SECONDARY_BULLETS" IsInteractive ="false" ObjectiveTrigger="ObjectivePickupHandgunBullets_Level_106" BulletCount="30" Position="1.4711,-2.811,23.2403" 		Rotation="0.0,-114.941,0.0"/>
		<Task ID="3" TaskType="TaskItem" Code="Activate" Item_ID="FN57Bullets_3" ItemType="ITEM_SECONDARY_BULLETS" IsInteractive ="false" ObjectiveTrigger="ObjectivePickupHandgunBullets_Level_106" BulletCount="30" Position="1.522,-2.811,25.17" 		Rotation="0.0,-210.307,0.0"/>
		<Task ID="4" TaskType="TaskItem" Code="Activate" Item_ID="FN57Bullets_4" ItemType="ITEM_SECONDARY_BULLETS" IsInteractive ="false" ObjectiveTrigger="ObjectivePickupHandgunBullets_Level_106" BulletCount="30" Position="-2.4524,-2.4201,22.748" 	Rotation="0.0,-300.239,0.0"/>
		<Task ID="5" TaskType="TaskItem" Code="Activate" Item_ID="FN57Bullets_5" ItemType="ITEM_SECONDARY_BULLETS" IsInteractive ="false" ObjectiveTrigger="ObjectivePickupHandgunBullets_Level_106" BulletCount="30" Position="-2.3111,-2.4201,22.9015" 	Rotation="0.0,-251.31,0.0"/>
		
		
		<!-- Primary Ammo -->
		<Task ID="1" TaskType="TaskItem" Code="Activate" Item_ID="AssaultBullets_1" ItemType="ITEM_PRIMARY_ASSAULT_BULLETS" ObjectiveTrigger="ObjectivePickupAssaultBullets" IsInteractive ="false" BulletCount="30" Position="1.5571,-2.7911,26.5644" Rotation="0.0,19.124,0.0"/>
		<Task ID="2" TaskType="TaskItem" Code="Activate" Item_ID="AssaultBullets_2" ItemType="ITEM_PRIMARY_ASSAULT_BULLETS" ObjectiveTrigger="ObjectivePickupAssaultBullets" IsInteractive ="false" BulletCount="30" Position="1.623,-2.7911,28.1199" Rotation="0.0,-53.676,0.0"/>
		<Task ID="3" TaskType="TaskItem" Code="Activate" Item_ID="AssaultBullets_3" ItemType="ITEM_PRIMARY_ASSAULT_BULLETS" ObjectiveTrigger="ObjectivePickupAssaultBullets" IsInteractive ="false" BulletCount="30" Position="-3.873,-2.5681,29.037" Rotation="0.0,-191.218,0.0"/>
		<Task ID="4" TaskType="TaskItem" Code="Activate" Item_ID="AssaultBullets_4" ItemType="ITEM_PRIMARY_ASSAULT_BULLETS" ObjectiveTrigger="ObjectivePickupAssaultBullets" IsInteractive ="false" BulletCount="30" Position="-3.996,-2.5681,26.712" Rotation="0.0,-159.395,0.0"/>
		<Task ID="5" TaskType="TaskItem" Code="Activate" Item_ID="AssaultBullets_5" ItemType="ITEM_PRIMARY_ASSAULT_BULLETS" ObjectiveTrigger="ObjectivePickupAssaultBullets" IsInteractive ="false" BulletCount="30" Position="-2.605,-2.7524,23.008" Rotation="0.0,-288.307,0.0"/>
		<Task ID="6" TaskType="TaskItem" Code="Activate" Item_ID="AssaultBullets_6" ItemType="ITEM_PRIMARY_ASSAULT_BULLETS" ObjectiveTrigger="ObjectivePickupAssaultBullets" IsInteractive ="false" BulletCount="30" Position="-2.826,-2.7524,22.976" Rotation="0.0,-217.105,0.0"/>
		<Task ID="7" TaskType="TaskItem" Code="Activate" Item_ID="AssaultBullets_7" ItemType="ITEM_PRIMARY_ASSAULT_BULLETS" ObjectiveTrigger="ObjectivePickupAssaultBullets" IsInteractive ="false" BulletCount="30" Position="-2.288,-2.048,22.923" Rotation="0.0,-296.032,0.0"/>
		<Task ID="8" TaskType="TaskItem" Code="Activate" Item_ID="AssaultBullets_8" ItemType="ITEM_PRIMARY_ASSAULT_BULLETS" ObjectiveTrigger="ObjectivePickupAssaultBullets" IsInteractive ="false" BulletCount="30" Position="-2.54,-2.048,22.766" Rotation="0.0,-248.474,0.0"/>
		<Task ID="9" TaskType="TaskItem" Code="Activate" Item_ID="AssaultBullets_9" ItemType="ITEM_PRIMARY_ASSAULT_BULLETS" ObjectiveTrigger="ObjectivePickupAssaultBullets" IsInteractive ="false" BulletCount="30" Position="-2.79,-2.048,22.91" Rotation="0.0,-252.655,0.0"/>
		
		
		<!-- Objective 1, welcome -->
		<Task ID="0" TaskType="TaskUserInterface" Command="Show" UI="TRAINING_TIPS" Code="Welcome"/>
		<Task ID="1" TaskType="TaskWait" WaitTime="8.0"/>
		<Task ID="2" TaskType="TaskUserInterface" Command="Hide" UI="TRAINING_TIPS"/>
		
		<!-- Objective 2, movement -->
		<Task ID="0" TaskType="TaskGameObject" IsActive="true" GameObject_ID="ObjectiveTrigger_Level_101" />
		<Task ID="1" TaskType="TaskUserInterface" Command="Show" UI="TRAINING_TIPS" Code="Movement"/>
		<Task ID="2" TaskType="TaskPlayer" Code="SetPlayerState" PlayerState="IN_GAME_MOVEMENT"/>
		<Task ID="3" TaskType="TaskWait" WaitTime="15.0"/>
		<Task ID="4" TaskType="TaskUserInterface" Command="Hide" UI="TRAINING_TIPS"/>
	</Sequence>
	
	<Sequence ID = "Training_100_OnEnd" >
		<Task ID="0" TaskType="TaskGameObject" IsActive="false" GameObject_ID="ObjectiveTrigger_Level_101" />
		<Task ID="1" TaskType="TaskUserInterface" Command="Hide" UI="TRAINING_TIPS"/>
	</Sequence>
	
<!-- Training_100 END-->

<!-- Training_101 START-->

	<Sequence ID = "Training_101_OnBegin" >
		<!-- Pick up Helmet -->
	    <Task ID="1" TaskType="TaskItem" Code="Activate" Item_ID="HELMET_Locker_Item" ItemType="ITEM_HELMET" ObjectiveTrigger="ObjectivePickupHelmet_Level_102" StrengthPercentage="100" Position="-5.824,0.779,-7.222" Rotation="-9,90,0.0"/>
		<Task ID="2" TaskType="TaskUserInterface" Command="Show" UI="TRAINING_TIPS" Code="Helmet"/>
		<Task ID="3" TaskType="TaskWait" WaitTime="15.0"/>
		<Task ID="4" TaskType="TaskUserInterface" Command="Hide" UI="TRAINING_TIPS"/>
	</Sequence>
	
	<Sequence ID = "Training_101_OnEnd" >
	</Sequence>
	
<!-- Training_101 END-->

<!-- Training_102 START - Find the keycode and unlock door-->

	<Sequence ID = "Training_102_OnBegin" >
		<!-- Activate the door knob and key code interactive items, should not be activated on start -->
		<Task ID="1" TaskType="TaskGameObject" IsActive="true" GameObject_ID="Level102_LockedDoorPart1" />
		<Task ID="2" TaskType="TaskGameObject" IsActive="true" GameObject_ID="Level102_LockedDoorPart2" />
		
		<Task ID="3" TaskType="TaskUserInterface" Command="Show" UI="TRAINING_TIPS" Code="LockedDoor"/>
		<Task ID="4" TaskType="TaskWait" WaitTime="8.0"/>
		<Task ID="5" TaskType="TaskUserInterface" Command="Hide" UI="TRAINING_TIPS"/>
		<Task ID="6" TaskType="TaskAudio" AudClip="TrainingProceedToBunker" IsStart="true" IsLoop="false" Volume="1.0" SrcType="AUD_SRC_SFX" IsPooled="false" GameObjID="TrainingSpeaker"/>
	</Sequence>
	
	<Sequence ID = "Training_102_OnEnd" >
		<Task ID="0" TaskType="TaskGameObject" IsActive="true" GameObject_ID="ObjectiveTrigger_Level_103" />
		<Task ID="1" TaskType="TaskEnvironmentInteraction" Code="Door" IsLocked="true" GameObject_ID="Level102_LockedDoor" />
	</Sequence>
	
<!-- Training_102 END-->


<!-- Training_103 START - Go to the shooting range-->

	<Sequence ID = "Training_103_OnBegin" >
		<Task ID="0" TaskType="TaskUserInterface" Command="Show" UI="TRAINING_TIPS" Code="WalkToShootingRange"/>
		<Task ID="1" TaskType="TaskWait" WaitTime="4.0"/>
		<Task ID="2" TaskType="TaskUserInterface" Command="Hide" UI="TRAINING_TIPS"/>
	</Sequence>
	
	<Sequence ID = "Training_103_OnEnd" >
		<Task ID="0" TaskType="TaskEnvironmentInteraction" Code="Door" IsLocked="true" GameObject_ID="Level103_LockedDoor" />
	</Sequence>
	
<!-- Training_103 END-->

<!-- Training_104 START - Pick up a pistol-->

	<Sequence ID = "Training_104_OnBegin" >
		<Task ID="0" TaskType="TaskUserInterface" Command="Show" UI="TRAINING_TIPS" Code="PickupHandgun"/>
		<Task ID="1" TaskType="TaskWait" WaitTime="15.0"/>
		<Task ID="2" TaskType="TaskUserInterface" Command="Hide" UI="TRAINING_TIPS"/>
	</Sequence>
	
	<Sequence ID = "Training_104_OnEnd" >
		<Task ID="0" TaskType="TaskUserInterface" Command="Hide" UI="TRAINING_TIPS"/>
	</Sequence>
	
<!-- Training_104 END-->

<!-- Training_105 START - Pick up handgun bullets-->

	<Sequence ID = "Training_105_OnBegin" >
		<Task ID="0" TaskType="TaskItem" Code="Interaction" Item_ID="FN57Bullets_1" ItemType="ITEM_SECONDARY_BULLETS" IsInteractive ="true" />
		<Task ID="1" TaskType="TaskItem" Code="Interaction" Item_ID="FN57Bullets_2" ItemType="ITEM_SECONDARY_BULLETS" IsInteractive ="true" />
		<Task ID="2" TaskType="TaskItem" Code="Interaction" Item_ID="FN57Bullets_3" ItemType="ITEM_SECONDARY_BULLETS" IsInteractive ="true" />
		<Task ID="3" TaskType="TaskItem" Code="Interaction" Item_ID="FN57Bullets_4" ItemType="ITEM_SECONDARY_BULLETS" IsInteractive ="true" />
		<Task ID="4" TaskType="TaskItem" Code="Interaction" Item_ID="FN57Bullets_5" ItemType="ITEM_SECONDARY_BULLETS" IsInteractive ="true" />
		<Task ID="5" TaskType="TaskUserInterface" Command="Show" UI="TRAINING_TIPS" Code="PickupHandgunBullets"/>
		<Task ID="6" TaskType="TaskWait" WaitTime="10.0"/>
		<Task ID="7" TaskType="TaskUserInterface" Command="Hide" UI="TRAINING_TIPS"/>
	</Sequence>
	
	<Sequence ID = "Training_105_OnEnd" >
	</Sequence>
	
<!-- Training_105 END-->


<!-- Training_106 START - RELOAD Weapon -->

	<Sequence ID = "Training_106_OnBegin" >
		<Task ID="0" TaskType="TaskUserInterface" Command="Show" UI="TRAINING_TIPS" Code="ReloadHandgun"/>
		<Task ID="1" TaskType="TaskWait" WaitTime="10.0"/>
		<Task ID="2" TaskType="TaskUserInterface" Command="Hide" UI="TRAINING_TIPS"/>
	</Sequence>
	
	<Sequence ID = "Training_106_OnEnd" >
	</Sequence>
	
<!-- Training_106 END-->


<!-- Training_107 START - Pickup assault -->

	<Sequence ID = "Training_107_OnBegin" >
		<Task ID="0" TaskType="TaskItem" Code="Interaction" Item_ID="AK47_Bunker_Item" ItemType="ITEM_AK47" IsInteractive ="true" />
		<Task ID="1" TaskType="TaskItem" Code="Interaction" Item_ID="Thompson_Bunker_Item" ItemType="ITEM_THOMPSON" IsInteractive ="true" />
		<Task ID="2" TaskType="TaskUserInterface" Command="Show" UI="TRAINING_TIPS" Code="PickupAssaultWeapon1"/>
		<Task ID="3" TaskType="TaskWait" WaitTime="8.0"/>
		<Task ID="4" TaskType="TaskUserInterface" Command="Hide" UI="TRAINING_TIPS"/>
	</Sequence>
	
	<Sequence ID = "Training_107_OnEnd" >
	</Sequence>
	
<!-- Training_107 END-->

<!-- Training_108 START - Pickup assault 2 -->

	<Sequence ID = "Training_108_OnBegin" >
		<Task ID="0" TaskType="TaskUserInterface" Command="Show" UI="TRAINING_TIPS" Code="PickupAssaultWeapon2"/>
		<Task ID="1" TaskType="TaskWait" WaitTime="8.0"/>
		<Task ID="2" TaskType="TaskUserInterface" Command="Hide" UI="TRAINING_TIPS"/>
	</Sequence>
	
	<Sequence ID = "Training_108_OnEnd" >
	</Sequence>
	
<!-- Training_108 END-->

<!-- Training_109 START - Pickup assault bullets -->

	<Sequence ID = "Training_109_OnBegin" >
		<Task ID="0" TaskType="TaskItem" Code="Interaction" Item_ID="AssaultBullets_1" ItemType="ITEM_PRIMARY_ASSAULT_BULLETS" IsInteractive ="true"/>
		<Task ID="1" TaskType="TaskItem" Code="Interaction" Item_ID="AssaultBullets_2" ItemType="ITEM_PRIMARY_ASSAULT_BULLETS" IsInteractive ="true"/>
		<Task ID="2" TaskType="TaskItem" Code="Interaction" Item_ID="AssaultBullets_3" ItemType="ITEM_PRIMARY_ASSAULT_BULLETS" IsInteractive ="true"/>
		<Task ID="3" TaskType="TaskItem" Code="Interaction" Item_ID="AssaultBullets_4" ItemType="ITEM_PRIMARY_ASSAULT_BULLETS" IsInteractive ="true"/>
		<Task ID="4" TaskType="TaskItem" Code="Interaction" Item_ID="AssaultBullets_5" ItemType="ITEM_PRIMARY_ASSAULT_BULLETS" IsInteractive ="true"/>
		<Task ID="5" TaskType="TaskItem" Code="Interaction" Item_ID="AssaultBullets_6" ItemType="ITEM_PRIMARY_ASSAULT_BULLETS" IsInteractive ="true"/>
		<Task ID="6" TaskType="TaskItem" Code="Interaction" Item_ID="AssaultBullets_7" ItemType="ITEM_PRIMARY_ASSAULT_BULLETS" IsInteractive ="true"/>
		<Task ID="7" TaskType="TaskItem" Code="Interaction" Item_ID="AssaultBullets_8" ItemType="ITEM_PRIMARY_ASSAULT_BULLETS" IsInteractive ="true"/>
		<Task ID="8" TaskType="TaskItem" Code="Interaction" Item_ID="AssaultBullets_9" ItemType="ITEM_PRIMARY_ASSAULT_BULLETS" IsInteractive ="true"/>	
		<Task ID="9" TaskType="TaskUserInterface" Command="Show" UI="TRAINING_TIPS" Code="PickupAssaultBullets"/>
		<Task ID="10" TaskType="TaskWait" WaitTime="8.0"/>
		<Task ID="11" TaskType="TaskUserInterface" Command="Hide" UI="TRAINING_TIPS"/>
	</Sequence>
	
	<Sequence ID = "Training_109_OnEnd" >
	</Sequence>
	
<!-- Training_109 END-->

<!-- Training_110 START - Reload assault -->

	<Sequence ID = "Training_110_OnBegin" >
		<Task ID="9" TaskType="TaskUserInterface" Command="Show" UI="TRAINING_TIPS" Code="ReloadAssault"/>
		<Task ID="10" TaskType="TaskWait" WaitTime="4.0"/>
		<Task ID="11" TaskType="TaskUserInterface" Command="Hide" UI="TRAINING_TIPS"/>
	</Sequence>
	
	<Sequence ID = "Training_110_OnEnd" >
	</Sequence>
	
<!-- Training_110 END-->

<!-- Training_111 START - Switch weapon -->

	<Sequence ID = "Training_111_OnBegin" >
		<Task ID="9" TaskType="TaskUserInterface" Command="Show" UI="TRAINING_TIPS" Code="SwitchWeapon"/>
		<Task ID="10" TaskType="TaskWait" WaitTime="15.0"/>
		<Task ID="11" TaskType="TaskUserInterface" Command="Hide" UI="TRAINING_TIPS"/>
	</Sequence>
	
	<Sequence ID = "Training_111_OnEnd" >
	</Sequence>
	
<!-- Training_111 END-->


<!-- Training_112 START - Go to the shooting range highlighted -->

	<Sequence ID = "Training_112_OnBegin" >
		<Task ID="0" TaskType="TaskGameObject" IsActive="true" GameObject_ID="ObjectiveTrigger_Level_112" />
		<Task ID="1" TaskType="TaskUserInterface" Command="Show" UI="TRAINING_TIPS" Code="ShootingRangeHighlighted"/>
		<Task ID="2" TaskType="TaskWait" WaitTime="8.0"/>
		<Task ID="3" TaskType="TaskUserInterface" Command="Hide" UI="TRAINING_TIPS"/>
	</Sequence>
	
	<Sequence ID = "Training_112_OnEnd" >
		<Task ID="0" TaskType="TaskGameObject" IsActive="false" GameObject_ID="ObjectiveTrigger_Level_112" />
	</Sequence>
	
<!-- Training_112 END-->

<!-- Training_113 START - Fire at all the targets -->

	<Sequence ID = "Training_113_OnBegin" >
		<!-- Position Dummy targets for the 1st shooting level here -->
		<Task ID="0" TaskType="TaskSetTransform" GameObject_ID="DummyTarget1" Position="3.855,-2.9054,25.239" 	 Rotation="0.0,0.0,0.0" Scale="1.0,1.0,1.0" />
		<Task ID="1" TaskType="TaskSetTransform" GameObject_ID="DummyTarget2" Position="4.501,-2.9054,23.042" 	 Rotation="0.0,0.0,0.0" Scale="1.0,1.0,1.0" />
		<Task ID="2" TaskType="TaskSetTransform" GameObject_ID="DummyTarget3" Position="5.272,-2.9054,24.753" 		 Rotation="0.0,0.0,0.0" Scale="1.0,1.0,1.0" />
		<Task ID="3" TaskType="TaskSetTransform" GameObject_ID="DummyTarget4" Position="5.823,-2.9054,23.555" 		 Rotation="0.0,0.0,0.0" Scale="1.0,1.0,1.0" />
		<Task ID="4" TaskType="TaskSetTransform" GameObject_ID="DummyTarget5" Position="6.863,-2.9054,24.233" 	 Rotation="0.0,0.0,0.0" Scale="1.0,1.0,1.0" />
	              
		<Task ID="5" TaskType="TaskUserInterface" Command="Show" UI="TRAINING_TIPS" Code="FireAtTarget1"/>
		<Task ID="6" TaskType="TaskWait" WaitTime="14.0"/>
		<Task ID="7" TaskType="TaskUserInterface" Command="Hide" UI="TRAINING_TIPS"/>
	</Sequence>
	
	<Sequence ID = "Training_113_OnEnd" >
	</Sequence>
	
<!-- Training_113 END-->

<!-- Training_114 START - Fire at all the targets -->

	<Sequence ID = "Training_114_OnBegin" >
		<!-- Position Dummy targets for the 2nd shooting level here -->
		<Task ID="0" TaskType="TaskSetTransform" GameObject_ID="DummyTarget1" Position="5.807,-2.9054,25.239" 	 Rotation="0.0,0.0,0.0" Scale="1.0,1.0,1.0" />
		<Task ID="1" TaskType="TaskSetTransform" GameObject_ID="DummyTarget2" Position="5.166,-2.9054,23.912" 	 Rotation="0.0,0.0,0.0" Scale="1.0,1.0,1.0" />
		<Task ID="2" TaskType="TaskSetTransform" GameObject_ID="DummyTarget3" Position="7.917,-2.9054,24.75" 		 Rotation="0.0,0.0,0.0" Scale="1.0,1.0,1.0" />
		<Task ID="3" TaskType="TaskSetTransform" GameObject_ID="DummyTarget4" Position="6.424,-2.9054,23.12" 		 Rotation="0.0,0.0,0.0" Scale="1.0,1.0,1.0" />
		<Task ID="4" TaskType="TaskSetTransform" GameObject_ID="DummyTarget5" Position="9.41,-2.9054,23.87" 	 Rotation="0.0,0.0,0.0" Scale="1.0,1.0,1.0" />
	              
		<Task ID="5" TaskType="TaskUserInterface" Command="Show" UI="TRAINING_TIPS" Code="FireAtTarget2"/>
		<Task ID="6" TaskType="TaskWait" WaitTime="14.0"/>
		<Task ID="7" TaskType="TaskUserInterface" Command="Hide" UI="TRAINING_TIPS"/>
	</Sequence>
	
	<Sequence ID = "Training_114_OnEnd" >
	</Sequence>
	
<!-- Training_114 END-->

<!-- Training_115 START - Fire at all the targets -->

	<Sequence ID = "Training_115_OnBegin" >
		<!-- Position Dummy targets for the 3rd shooting level here -->
		<Task ID="0" TaskType="TaskSetTransform" GameObject_ID="DummyTarget1" Position="5.63,-2.9054,24.67" 	Rotation="0.0,0.0,0.0" Scale="1.0,1.0,1.0" />
		<Task ID="1" TaskType="TaskSetTransform" GameObject_ID="DummyTarget2" Position="9.8,-2.9054,23.912" 	Rotation="0.0,0.0,0.0" Scale="1.0,1.0,1.0" />
		<Task ID="2" TaskType="TaskSetTransform" GameObject_ID="DummyTarget3" Position="7.47,-2.9054,23.085" 		Rotation="0.0,0.0,0.0" Scale="1.0,1.0,1.0" />
		<Task ID="3" TaskType="TaskSetTransform" GameObject_ID="DummyTarget4" Position="11.73,-2.9054,25.335" 		Rotation="0.0,0.0,0.0" Scale="1.0,1.0,1.0" />
		<Task ID="4" TaskType="TaskSetTransform" GameObject_ID="DummyTarget5" Position="14.56,-2.9054,24.462" 	Rotation="0.0,0.0,0.0" Scale="1.0,1.0,1.0" />
	              
		<Task ID="5" TaskType="TaskUserInterface" Command="Show" UI="TRAINING_TIPS" Code="FireAtTarget3"/>
		<Task ID="6" TaskType="TaskWait" WaitTime="14.0"/>
		<Task ID="7" TaskType="TaskUserInterface" Command="Hide" UI="TRAINING_TIPS"/>
	</Sequence>
	
	<Sequence ID = "Training_115_OnEnd" >
	</Sequence>
	
<!-- Training_115 END-->

<!-- Training_116 START - Fire at all the targets -->

	<Sequence ID = "Training_116_OnBegin" >
		<!-- Position Dummy targets for the 4th shooting level here -->
		<Task ID="0" TaskType="TaskSetTransform" GameObject_ID="DummyTarget1" Position="4.037,-2.9054,24.208" 	 Rotation="0.0,0.0,0.0" Scale="1.0,1.0,1.0" />
		<Task ID="1" TaskType="TaskSetTransform" GameObject_ID="DummyTarget2" Position="9.8,-2.9054,25.212" 	 Rotation="0.0,0.0,0.0" Scale="1.0,1.0,1.0" />
		<Task ID="2" TaskType="TaskSetTransform" GameObject_ID="DummyTarget3" Position="7.47,-2.9054,24.208" 		 Rotation="0.0,0.0,0.0" Scale="1.0,1.0,1.0" />
		<Task ID="3" TaskType="TaskSetTransform" GameObject_ID="DummyTarget4" Position="12.5,-2.9054,23.2" 		 Rotation="0.0,0.0,0.0" Scale="1.0,1.0,1.0" />
		<Task ID="4" TaskType="TaskSetTransform" GameObject_ID="DummyTarget5" Position="15.6,-2.9054,24.208" 	 Rotation="0.0,0.0,0.0" Scale="1.0,1.0,1.0" />
	
		<Task ID="5" TaskType="TaskUserInterface" Command="Show" UI="TRAINING_TIPS" Code="FireAtTarget4"/>
		<Task ID="6" TaskType="TaskWait" WaitTime="14.0"/>
		<Task ID="7" TaskType="TaskUserInterface" Command="Hide" UI="TRAINING_TIPS"/>
	</Sequence>
	
	<Sequence ID = "Training_116_OnEnd" >
	</Sequence>
	
<!-- Training_116 END-->

<!-- Training_117 START - exit the training session through the door -->

	<Sequence ID = "Training_117_OnBegin" >
		<Task ID="0" TaskType="TaskEnvironmentInteraction" Code="Door" IsLocked="false" GameObject_ID="TrainingExitDoor" />
		<Task ID="9" TaskType="TaskUserInterface" Command="Show" UI="TRAINING_TIPS" Code="ExitTraining"/>
		<Task ID="10" TaskType="TaskWait" WaitTime="8.0"/>
		<Task ID="11" TaskType="TaskUserInterface" Command="Hide" UI="TRAINING_TIPS"/>
	</Sequence>
	
	<Sequence ID = "Training_117_OnEnd" >
	</Sequence>
	
<!-- Training_117 END-->
</TaskList>